Metadata-Version: 1.1
Name: picosat-cffi
Version: 0.0.1
Summary: Low-level CFFI bindings for PicoSAT
Home-page: http://bitbucket.org/dholth/picosat-cffi/
Author: Daniel Holth
Author-email: dholth@gmail.com
License: MIT
Keywords: picosat sat
Platform: UNKNOWN
Classifier: Programming Language :: Python
Classifier: Programming Language :: Python :: 2
Classifier: Programming Language :: Python :: 2.7
Classifier: Programming Language :: Python :: 3
Classifier: Programming Language :: Python :: 3.3
